{
    "id": 1,
    "name": "Level 1",
    "group": "group1",
    "tableComboRange": [
        6,
        7
    ],
    "minBreakDiff": 2,
    "tableCards": [
        {
            "value": 0,
            "type": 3,
            "tAngle": 0,
            "tIdx": 0,
            "tLayer": 1,
            "tPos": {
                "x": 51,
                "y": 75,
                "z": 0
            }
        },
        {
            "value": 0,
            "type": 3,
            "tAngle": 0,
            "tIdx": 1,
            "tLayer": 2,
            "tPos": {
                "x": -25.5,
                "y": 50,
                "z": 0
            }
        },
        {
            "value": 0,
            "type": 3,
            "tAngle": 0,
            "tIdx": 2,
            "tLayer": 2,
            "tPos": {
                "x": 127.5,
                "y": 50,
                "z": 0
            }
        },
        {
            "value": 0,
            "type": 3,
            "tAngle": 0,
            "tIdx": 3,
            "tLayer": 3,
            "tPos": {
                "x": 51,
                "y": -25,
                "z": 0
            }
        },
        {
            "value": 0,
            "type": 3,
            "tAngle": 0,
            "tIdx": 4,
            "tLayer": 3,
            "tPos": {
                "x": -51,
                "y": -25,
                "z": 0
            }
        },
        {
            "value": 0,
            "type": 3,
            "tAngle": 0,
            "tIdx": 5,
            "tLayer": 4,
            "tPos": {
                "x": 153,
                "y": -25,
                "z": 0
            }
        },
        {
            "value": 0,
            "type": 3,
            "tAngle": 0,
            "tIdx": 6,
            "tLayer": 4,
            "tPos": {
                "x": -76.5,
                "y": -75,
                "z": 0
            }
        },
        {
            "value": 0,
            "type": 3,
            "tAngle": 0,
            "tIdx": 7,
            "tLayer": 4,
            "tPos": {
                "x": 25.5,
                "y": -75,
                "z": 0
            }
        },
        {
            "value": 0,
            "type": 3,
            "tAngle": 0,
            "tIdx": 8,
            "tLayer": 5,
            "tPos": {
                "x": 127.5,
                "y": -75,
                "z": 0
            }
        },
        {
            "value": 0,
            "type": 3,
            "tAngle": 0,
            "tIdx": 9,
            "tLayer": 5,
            "tPos": {
                "x": 229.5,
                "y": -75,
                "z": 0
            }
        }
    ],
    "maxComboRedProb": 0.5,
    "breakSwitchProb": 0.5,
    "poolCount": 10,
    "handCardValue": 0,
    "minGuarantee": 3
}